HardwareDesign/Audiosystem/Old/lerper.v
module lerper #(
    parameter SIGNAL_WIDTH = 16
) (
    input clk,
    input rstn,

    input[SIGNAL_WIDTH - 1 : 0] i_signal,
    input[15:0] speed, //Signed int. Negative numbers are interpreted as fractional slowdown. E.g. -4 is interpreted as a speed of 0.25. A speed of 0 will cause the output to be equal to the input.

    output reg[SIGNAL_WIDTH - 1 : 0] o_signal
);

localparam IDLE = 0;
localparam FASTER = 1;
localparam SLOWER = 2;
localparam FINISH = 4;

wire[SIGNAL_WIDTH - 1 : 0] signal_delta = o_signal - i_signal;
reg[3:0] state = 0;

wire[15:0] slow_speed = -speed;
wire slow_tick = slower_counter == 0;
reg[15:0] slower_counter = 0;

always @(posedge clk) begin
    if(rstn == 0) begin
        state <= 0;
    end else begin
        case(state)
            IDLE: begin
                if(signal_delta != 0)
                    state <= $signed(speed) < 0 ? SLOWER : $signed(speed) > 0 ? FASTER  : IDLE; 
                if(speed == 0)
                    state <= FINISH;
            end
            FASTER: begin
                if(($signed(signal_delta) < $signed(speed) && $signed(signal_delta) > $signed(-speed)) || speed == 0) 
                    state <= FINISH;
                else if ($signed(speed) < 0)
                    state <= SLOWER;
            end
            SLOWER: begin
                if(($signed(signal_delta) == 0) || speed == 0)
                    state <= FINISH;
                else if($signed(speed) > 0)
                    state <= FASTER;
            end
            FINISH: begin
                state <= IDLE;
            end
        endcase
    end
end

always @(posedge clk) begin
    if(rstn == 0) begin
        o_signal <= i_signal;
        slower_counter = 0;
    end else begin
        case (state)
            IDLE: begin
                if(speed == 0)
                    o_signal <= i_signal;
                slower_counter <= 0;
            end
            FASTER: begin
                if($signed(signal_delta) < 0)
                    o_signal <= o_signal + speed;
                else if($signed(signal_delta) > 0)
                    o_signal <= o_signal - speed;
            end
            SLOWER: begin
                if(slow_tick) begin 
                    if($signed(signal_delta) < 0)
                        o_signal <= o_signal + 1;
                    else if($signed(signal_delta) > 0)
                        o_signal <= o_signal - 1;
                end
            end
            FINISH: begin
                o_signal <= i_signal;
            end
        endcase
    end
end

always @(posedge clk) begin
    if(rstn == 0) begin
        slower_counter <= 0;
    end else begin
        if($signed(speed) > 0) begin
            slower_counter <= 0;
        end else begin
            slower_counter <= slower_counter + 1;
            if(slower_counter + 1 == slow_speed) begin
                slower_counter <= 0;
            end
        end
    end
end

endmodule

HardwareDesign/Audiosystem/Old/lerper_tb.v
`timescale 1ns/1ns

module main_tb (
);

reg clk = 0;
reg rstn = 0;
reg[15:0] i_signal = 'h0000;
reg[15:0] speed = 3;

wire[15:0] o_signal;

lerper lerper 
(
    .clk(clk),
    .rstn(rstn),

    .i_signal(i_signal),
    .speed(speed),
    .o_signal(o_signal)
);

always @(clk) begin
    #1 clk <= ~clk;
end

initial begin
    $dumpvars(0, main_tb);
    
    #2 clk <= 1;

    rstn <= 1;
    i_signal <= 5000;
    #10000

    i_signal <= 0;
    #10000

    speed <= -3;
    i_signal <= 5000;
    #100000

    i_signal <= 0;
    #100000

    $finish;
end

endmodule

HardwareDesign/Audiosystem/Old/dump.vcd
$date
	Fri Oct 11 22:28:06 2024
$end
$version
	Icarus Verilog
$end
$timescale
	1ns
$end
$scope module main_tb $end
$var wire 16 ! o_signal [15:0] $end
$var reg 1 " clk $end
$var reg 16 # i_signal [15:0] $end
$var reg 1 $ rstn $end
$var reg 16 % speed [15:0] $end
$scope module lerper $end
$var wire 1 " clk $end
$var wire 16 & i_signal [15:0] $end
$var wire 1 $ rstn $end
$var wire 16 ' speed [15:0] $end
$var wire 1 ( slow_tick $end
$var wire 16 ) slow_speed [15:0] $end
$var wire 16 * signal_delta [15:0] $end
$var parameter 32 + FASTER $end
$var parameter 32 , FINISH $end
$var parameter 32 - IDLE $end
$var parameter 32 . SIGNAL_WIDTH $end
$var parameter 32 / SLOWER $end
$var reg 16 0 o_signal [15:0] $end
$var reg 16 1 slower_counter [15:0] $end
$var reg 4 2 state [3:0] $end
$upscope $end
$upscope $end
$enddefinitions $end
$comment Show the parameter values. $end
$dumpall
b10 /
b10000 .
b0 -
b100 ,
b1 +
$end
#0
$dumpvars
b0 2
b0 1
bx 0
bx *
b1111111111111101 )
1(
b11 '
b0 &
b11 %
0$
b0 #
0"
bx !
$end
#1
b0 *
b0 !
b0 0
1"
#2
0"
b1110110001111000 *
b1001110001000 #
b1001110001000 &
1$
#3
b1 2
1"
#4
0"
#5
b1110110001111011 *
b11 !
b11 0
1"
#6
0"
#7
b1110110001111110 *
b110 !
b110 0
1"
#8
0"
#9
b1110110010000001 *
b1001 !
b1001 0
1"
#10
0"
#11
b1110110010000100 *
b1100 !
b1100 0
1"
#12
0"
#13
b1110110010000111 *
b1111 !
b1111 0
1"
#14
0"
#15
b1110110010001010 *
b10010 !
b10010 0
1"
#16
0"
#17
b1110110010001101 *
b10101 !
b10101 0
1"
#18
0"
#19
b1110110010010000 *
b11000 !
b11000 0
1"
#20
0"
#21
b1110110010010011 *
b11011 !
b11011 0
1"
#22
0"
#23
b1110110010010110 *
b11110 !
b11110 0
1"
#24
0"
#25
b1110110010011001 *
b100001 !
b100001 0
1"
#26
0"
#27
b1110110010011100 *
b100100 !
b100100 0
1"
#28
0"
#29
b1110110010011111 *
b100111 !
b100111 0
1"
#30
0"
#31
b1110110010100010 *
b101010 !
b101010 0
1"
#32
0"
#33
b1110110010100101 *
b101101 !
b101101 0
1"
#34
0"
#35
b1110110010101000 *
b110000 !
b110000 0
1"
#36
0"
#37
b1110110010101011 *
b110011 !
b110011 0
1"
#38
0"
#39
b1110110010101110 *
b110110 !
b110110 0
1"
#40
0"
#41
b1110110010110001 *
b111001 !
b111001 0
1"
#42
0"
#43
b1110110010110100 *
b111100 !
b111100 0
1"
#44
0"
#45
b1110110010110111 *
b111111 !
b111111 0
1"
#46
0"
#47
b1110110010111010 *
b1000010 !
b1000010 0
1"
#48
0"
#49
b1110110010111101 *
b1000101 !
b1000101 0
1"
#50
0"
#51
b1110110011000000 *
b1001000 !
b1001000 0
1"
#52
0"
#53
b1110110011000011 *
b1001011 !
b1001011 0
1"
#54
0"
#55
b1110110011000110 *
b1001110 !
b1001110 0
1"
#56
0"
#57
b1110110011001001 *
b1010001 !
b1010001 0
1"
#58
0"
#59
b1110110011001100 *
b1010100 !
b1010100 0
1"
#60
0"
#61
b1110110011001111 *
b1010111 !
b1010111 0
1"
#62
0"
#63
b1110110011010010 *
b1011010 !
b1011010 0
1"
#64
0"
#65
b1110110011010101 *
b1011101 !
b1011101 0
1"
#66
0"
#67
b1110110011011000 *
b1100000 !
b1100000 0
1"
#68
0"
#69
b1110110011011011 *
b1100011 !
b1100011 0
1"
#70
0"
#71
b1110110011011110 *
b1100110 !
b1100110 0
1"
#72
0"
#73
b1110110011100001 *
b1101001 !
b1101001 0
1"
#74
0"
#75
b1110110011100100 *
b1101100 !
b1101100 0
1"
#76
0"
#77
b1110110011100111 *
b1101111 !
b1101111 0
1"
#78
0"
#79
b1110110011101010 *
b1110010 !
b1110010 0
1"
#80
0"
#81
b1110110011101101 *
b1110101 !
b1110101 0
1"
#82
0"
#83
b1110110011110000 *
b1111000 !
b1111000 0
1"
#84
0"
#85
b1110110011110011 *
b1111011 !
b1111011 0
1"
#86
0"
#87
b1110110011110110 *
b1111110 !
b1111110 0
1"
#88
0"
#89
b1110110011111001 *
b10000001 !
b10000001 0
1"
#90
0"
#91
b1110110011111100 *
b10000100 !
b10000100 0
1"
#92
0"
#93
b1110110011111111 *
b10000111 !
b10000111 0
1"
#94
0"
#95
b1110110100000010 *
b10001010 !
b10001010 0
1"
#96
0"
#97
b1110110100000101 *
b10001101 !
b10001101 0
1"
#98
0"
#99
b1110110100001000 *
b10010000 !
b10010000 0
1"
#100
0"
#101
b1110110100001011 *
b10010011 !
b10010011 0
1"
#102
0"
#103
b1110110100001110 *
b10010110 !
b10010110 0
1"
#104
0"
#105
b1110110100010001 *
b10011001 !
b10011001 0
1"
#106
0"
#107
b1110110100010100 *
b10011100 !
b10011100 0
1"
#108
0"
#109
b1110110100010111 *
b10011111 !
b10011111 0
1"
#110
0"
#111
b1110110100011010 *
b10100010 !
b10100010 0
1"
#112
0"
#113
b1110110100011101 *
b10100101 !
b10100101 0
1"
#114
0"
#115
b1110110100100000 *
b10101000 !
b10101000 0
1"
#116
0"
#117
b1110110100100011 *
b10101011 !
b10101011 0
1"
#118
0"
#119
b1110110100100110 *
b10101110 !
b10101110 0
1"
#120
0"
#121
b1110110100101001 *
b10110001 !
b10110001 0
1"
#122
0"
#123
b1110110100101100 *
b10110100 !
b10110100 0
1"
#124
0"
#125
b1110110100101111 *
b10110111 !
b10110111 0
1"
#126
0"
#127
b1110110100110010 *
b10111010 !
b10111010 0
1"
#128
0"
#129
b1110110100110101 *
b10111101 !
b10111101 0
1"
#130
0"
#131
b1110110100111000 *
b11000000 !
b11000000 0
1"
#132
0"
#133
b1110110100111011 *
b11000011 !
b11000011 0
1"
#134
0"
#135
b1110110100111110 *
b11000110 !
b11000110 0
1"
#136
0"
#137
b1110110101000001 *
b11001001 !
b11001001 0
1"
#138
0"
#139
b1110110101000100 *
b11001100 !
b11001100 0
1"
#140
0"
#141
b1110110101000111 *
b11001111 !
b11001111 0
1"
#142
0"
#143
b1110110101001010 *
b11010010 !
b11010010 0
1"
#144
0"
#145
b1110110101001101 *
b11010101 !
b11010101 0
1"
#146
0"
#147
b1110110101010000 *
b11011000 !
b11011000 0
1"
#148
0"
#149
b1110110101010011 *
b11011011 !
b11011011 0
1"
#150
0"
#151
b1110110101010110 *
b11011110 !
b11011110 0
1"
#152
0"
#153
b1110110101011001 *
b11100001 !
b11100001 0
1"
#154
0"
#155
b1110110101011100 *
b11100100 !
b11100100 0
1"
#156
0"
#157
b1110110101011111 *
b11100111 !
b11100111 0
1"
#158
0"
#159
b1110110101100010 *
b11101010 !
b11101010 0
1"
#160
0"
#161
b1110110101100101 *
b11101101 !
b11101101 0
1"
#162
0"
#163
b1110110101101000 *
b11110000 !
b11110000 0
1"
#164
0"
#165
b1110110101101011 *
b11110011 !
b11110011 0
1"
#166
0"
#167
b1110110101101110 *
b11110110 !
b11110110 0
1"
#168
0"
#169
b1110110101110001 *
b11111001 !
b11111001 0
1"
#170
0"
#171
b1110110101110100 *
b11111100 !
b11111100 0
1"
#172
0"
#173
b1110110101110111 *
b11111111 !
b11111111 0
1"
#174
0"
#175
b1110110101111010 *
b100000010 !
b100000010 0
1"
#176
0"
#177
b1110110101111101 *
b100000101 !
b100000101 0
1"
#178
0"
#179
b1110110110000000 *
b100001000 !
b100001000 0
1"
#180
0"
#181
b1110110110000011 *
b100001011 !
b100001011 0
1"
#182
0"
#183
b1110110110000110 *
b100001110 !
b100001110 0
1"
#184
0"
#185
b1110110110001001 *
b100010001 !
b100010001 0
1"
#186
0"
#187
b1110110110001100 *
b100010100 !
b100010100 0
1"
#188
0"
#189
b1110110110001111 *
b100010111 !
b100010111 0
1"
#190
0"
#191
b1110110110010010 *
b100011010 !
b100011010 0
1"
#192
0"
#193
b1110110110010101 *
b100011101 !
b100011101 0
1"
#194
0"
#195
b1110110110011000 *
b100100000 !
b100100000 0
1"
#196
0"
#197
b1110110110011011 *
b100100011 !
b100100011 0
1"
#198
0"
#199
b1110110110011110 *
b100100110 !
b100100110 0
1"
#200
0"
#201
b1110110110100001 *
b100101001 !
b100101001 0
1"
#202
0"
#203
b1110110110100100 *
b100101100 !
b100101100 0
1"
#204
0"
#205
b1110110110100111 *
b100101111 !
b100101111 0
1"
#206
0"
#207
b1110110110101010 *
b100110010 !
b100110010 0
1"
#208
0"
#209
b1110110110101101 *
b100110101 !
b100110101 0
1"
#210
0"
#211
b1110110110110000 *
b100111000 !
b100111000 0
1"
#212
0"
#213
b1110110110110011 *
b100111011 !
b100111011 0
1"
#214
0"
#215
b1110110110110110 *
b100111110 !
b100111110 0
1"
#216
0"
#217
b1110110110111001 *
b101000001 !
b101000001 0
1"
#218
0"
#219
b1110110110111100 *
b101000100 !
b101000100 0
1"
#220
0"
#221
b1110110110111111 *
b101000111 !
b101000111 0
1"
#222
0"
#223
b1110110111000010 *
b101001010 !
b101001010 0
1"
#224
0"
#225
b1110110111000101 *
b101001101 !
b101001101 0
1"
#226
0"
#227
b1110110111001000 *
b101010000 !
b101010000 0
1"
#228
0"
#229
b1110110111001011 *
b101010011 !
b101010011 0
1"
#230
0"
#231
b1110110111001110 *
b101010110 !
b101010110 0
1"
#232
0"
#233
b1110110111010001 *
b101011001 !
b101011001 0
1"
#234
0"
#235
b1110110111010100 *
b101011100 !
b101011100 0
1"
#236
0"
#237
b1110110111010111 *
b101011111 !
b101011111 0
1"
#238
0"
#239
b1110110111011010 *
b101100010 !
b101100010 0
1"
#240
0"
#241
b1110110111011101 *
b101100101 !
b101100101 0
1"
#242
0"
#243
b1110110111100000 *
b101101000 !
b101101000 0
1"
#244
0"
#245
b1110110111100011 *
b101101011 !
b101101011 0
1"
#246
0"
#247
b1110110111100110 *
b101101110 !
b101101110 0
1"
#248
0"
#249
b1110110111101001 *
b101110001 !
b101110001 0
1"
#250
0"
#251
b1110110111101100 *
b101110100 !
b101110100 0
1"
#252
0"
#253
b1110110111101111 *
b101110111 !
b101110111 0
1"
#254
0"
#255
b1110110111110010 *
b101111010 !
b101111010 0
1"
#256
0"
#257
b1110110111110101 *
b101111101 !
b101111101 0
1"
#258
0"
#259
b1110110111111000 *
b110000000 !
b110000000 0
1"
#260
0"
#261
b1110110111111011 *
b110000011 !
b110000011 0
1"
#262
0"
#263
b1110110111111110 *
b110000110 !
b110000110 0
1"
#264
0"
#265
b1110111000000001 *
b110001001 !
b110001001 0
1"
#266
0"
#267
b1110111000000100 *
b110001100 !
b110001100 0
1"
#268
0"
#269
b1110111000000111 *
b110001111 !
b110001111 0
1"
#270
0"
#271
b1110111000001010 *
b110010010 !
b110010010 0
1"
#272
0"
#273
b1110111000001101 *
b110010101 !
b110010101 0
1"
#274
0"
#275
b1110111000010000 *
b110011000 !
b110011000 0
1"
#276
0"
#277
b1110111000010011 *
b110011011 !
b110011011 0
1"
#278
0"
#279
b1110111000010110 *
b110011110 !
b110011110 0
1"
#280
0"
#281
b1110111000011001 *
b110100001 !
b110100001 0
1"
#282
0"
#283
b1110111000011100 *
b110100100 !
b110100100 0
1"
#284
0"
#285
b1110111000011111 *
b110100111 !
b110100111 0
1"
#286
0"
#287
b1110111000100010 *
b110101010 !
b110101010 0
1"
#288
0"
#289
b1110111000100101 *
b110101101 !
b110101101 0
1"
#290
0"
#291
b1110111000101000 *
b110110000 !
b110110000 0
1"
#292
0"
#293
b1110111000101011 *
b110110011 !
b110110011 0
1"
#294
0"
#295
b1110111000101110 *
b110110110 !
b110110110 0
1"
#296
0"
#297
b1110111000110001 *
b110111001 !
b110111001 0
1"
#298
0"
#299
b1110111000110100 *
b110111100 !
b110111100 0
1"
#300
0"
#301
b1110111000110111 *
b110111111 !
b110111111 0
1"
#302
0"
#303
b1110111000111010 *
b111000010 !
b111000010 0
1"
#304
0"
#305
b1110111000111101 *
b111000101 !
b111000101 0
1"
#306
0"
#307
b1110111001000000 *
b111001000 !
b111001000 0
1"
#308
0"
#309
b1110111001000011 *
b111001011 !
b111001011 0
1"
#310
0"
#311
b1110111001000110 *
b111001110 !
b111001110 0
1"
#312
0"
#313
b1110111001001001 *
b111010001 !
b111010001 0
1"
#314
0"
#315
b1110111001001100 *
b111010100 !
b111010100 0
1"
#316
0"
#317
b1110111001001111 *
b111010111 !
b111010111 0
1"
#318
0"
#319
b1110111001010010 *
b111011010 !
b111011010 0
1"
#320
0"
#321
b1110111001010101 *
b111011101 !
b111011101 0
1"
#322
0"
#323
b1110111001011000 *
b111100000 !
b111100000 0
1"
#324
0"
#325
b1110111001011011 *
b111100011 !
b111100011 0
1"
#326
0"
#327
b1110111001011110 *
b111100110 !
b111100110 0
1"
#328
0"
#329
b1110111001100001 *
b111101001 !
b111101001 0
1"
#330
0"
#331
b1110111001100100 *
b111101100 !
b111101100 0
1"
#332
0"
#333
b1110111001100111 *
b111101111 !
b111101111 0
1"
#334
0"
#335
b1110111001101010 *
b111110010 !
b111110010 0
1"
#336
0"
#337
b1110111001101101 *
b111110101 !
b111110101 0
1"
#338
0"
#339
b1110111001110000 *
b111111000 !
b111111000 0
1"
#340
0"
#341
b1110111001110011 *
b111111011 !
b111111011 0
1"
#342
0"
#343
b1110111001110110 *
b111111110 !
b111111110 0
1"
#344
0"
#345
b1110111001111001 *
b1000000001 !
b1000000001 0
1"
#346
0"
#347
b1110111001111100 *
b1000000100 !
b1000000100 0
1"
#348
0"
#349
b1110111001111111 *
b1000000111 !
b1000000111 0
1"
#350
0"
#351
b1110111010000010 *
b1000001010 !
b1000001010 0
1"
#352
0"
#353
b1110111010000101 *
b1000001101 !
b1000001101 0
1"
#354
0"
#355
b1110111010001000 *
b1000010000 !
b1000010000 0
1"
#356
0"
#357
b1110111010001011 *
b1000010011 !
b1000010011 0
1"
#358
0"
#359
b1110111010001110 *
b1000010110 !
b1000010110 0
1"
#360
0"
#361
b1110111010010001 *
b1000011001 !
b1000011001 0
1"
#362
0"
#363
b1110111010010100 *
b1000011100 !
b1000011100 0
1"
#364
0"
#365
b1110111010010111 *
b1000011111 !
b1000011111 0
1"
#366
0"
#367
b1110111010011010 *
b1000100010 !
b1000100010 0
1"
#368
0"
#369
b1110111010011101 *
b1000100101 !
b1000100101 0
1"
#370
0"
#371
b1110111010100000 *
b1000101000 !
b1000101000 0
1"
#372
0"
#373
b1110111010100011 *
b1000101011 !
b1000101011 0
1"
#374
0"
#375
b1110111010100110 *
b1000101110 !
b1000101110 0
1"
#376
0"
#377
b1110111010101001 *
b1000110001 !
b1000110001 0
1"
#378
0"
#379
b1110111010101100 *
b1000110100 !
b1000110100 0
1"
#380
0"
#381
b1110111010101111 *
b1000110111 !
b1000110111 0
1"
#382
0"
#383
b1110111010110010 *
b1000111010 !
b1000111010 0
1"
#384
0"
#385
b1110111010110101 *
b1000111101 !
b1000111101 0
1"
#386
0"
#387
b1110111010111000 *
b1001000000 !
b1001000000 0
1"
#388
0"
#389
b1110111010111011 *
b1001000011 !
b1001000011 0
1"
#390
0"
#391
b1110111010111110 *
b1001000110 !
b1001000110 0
1"
#392
0"
#393
b1110111011000001 *
b1001001001 !
b1001001001 0
1"
#394
0"
#395
b1110111011000100 *
b1001001100 !
b1001001100 0
1"
#396
0"
#397
b1110111011000111 *
b1001001111 !
b1001001111 0
1"
#398
0"
#399
b1110111011001010 *
b1001010010 !
b1001010010 0
1"
#400
0"
#401
b1110111011001101 *
b1001010101 !
b1001010101 0
1"
#402
0"
#403
b1110111011010000 *
b1001011000 !
b1001011000 0
1"
#404
0"
#405
b1110111011010011 *
b1001011011 !
b1001011011 0
1"
#406
0"
#407
b1110111011010110 *
b1001011110 !
b1001011110 0
1"
#408
0"
#409
b1110111011011001 *
b1001100001 !
b1001100001 0
1"
#410
0"
#411
b1110111011011100 *
b1001100100 !
b1001100100 0
1"
#412
0"
#413
b1110111011011111 *
b1001100111 !
b1001100111 0
1"
#414
0"
#415
b1110111011100010 *
b1001101010 !
b1001101010 0
1"
#416
0"
#417
b1110111011100101 *
b1001101101 !
b1001101101 0
1"
#418
0"
#419
b1110111011101000 *
b1001110000 !
b1001110000 0
1"
#420
0"
#421
b1110111011101011 *
b1001110011 !
b1001110011 0
1"
#422
0"
#423
b1110111011101110 *
b1001110110 !
b1001110110 0
1"
#424
0"
#425
b1110111011110001 *
b1001111001 !
b1001111001 0
1"
#426
0"
#427
b1110111011110100 *
b1001111100 !
b1001111100 0
1"
#428
0"
#429
b1110111011110111 *
b1001111111 !
b1001111111 0
1"
#430
0"
#431
b1110111011111010 *
b1010000010 !
b1010000010 0
1"
#432
0"
#433
b1110111011111101 *
b1010000101 !
b1010000101 0
1"
#434
0"
#435
b1110111100000000 *
b1010001000 !
b1010001000 0
1"
#436
0"
#437
b1110111100000011 *
b1010001011 !
b1010001011 0
1"
#438
0"
#439
b1110111100000110 *
b1010001110 !
b1010001110 0
1"
#440
0"
#441
b1110111100001001 *
b1010010001 !
b1010010001 0
1"
#442
0"
#443
b1110111100001100 *
b1010010100 !
b1010010100 0
1"
#444
0"
#445
b1110111100001111 *
b1010010111 !
b1010010111 0
1"
#446
0"
#447
b1110111100010010 *
b1010011010 !
b1010011010 0
1"
#448
0"
#449
b1110111100010101 *
b1010011101 !
b1010011101 0
1"
#450
0"
#451
b1110111100011000 *
b1010100000 !
b1010100000 0
1"
#452
0"
#453
b1110111100011011 *
b1010100011 !
b1010100011 0
1"
#454
0"
#455
b1110111100011110 *
b1010100110 !
b1010100110 0
1"
#456
0"
#457
b1110111100100001 *
b1010101001 !
b1010101001 0
1"
#458
0"
#459
b1110111100100100 *
b1010101100 !
b1010101100 0
1"
#460
0"
#461
b1110111100100111 *
b1010101111 !
b1010101111 0
1"
#462
0"
#463
b1110111100101010 *
b1010110010 !
b1010110010 0
1"
#464
0"
#465
b1110111100101101 *
b1010110101 !
b1010110101 0
1"
#466
0"
#467
b1110111100110000 *
b1010111000 !
b1010111000 0
1"
#468
0"
#469
b1110111100110011 *
b1010111011 !
b1010111011 0
1"
#470
0"
#471
b1110111100110110 *
b1010111110 !
b1010111110 0
1"
#472
0"
#473
b1110111100111001 *
b1011000001 !
b1011000001 0
1"
#474
0"
#475
b1110111100111100 *
b1011000100 !
b1011000100 0
1"
#476
0"
#477
b1110111100111111 *
b1011000111 !
b1011000111 0
1"
#478
0"
#479
b1110111101000010 *
b1011001010 !
b1011001010 0
1"
#480
0"
#481
b1110111101000101 *
b1011001101 !
b1011001101 0
1"
#482
0"
#483
b1110111101001000 *
b1011010000 !
b1011010000 0
1"
#484
0"
#485
b1110111101001011 *
b1011010011 !
b1011010011 0
1"
#486
0"
#487
b1110111101001110 *
b1011010110 !
b1011010110 0
1"
#488
0"
#489
b1110111101010001 *
b1011011001 !
b1011011001 0
1"
#490
0"
#491
b1110111101010100 *
b1011011100 !
b1011011100 0
1"
#492
0"
#493
b1110111101010111 *
b1011011111 !
b1011011111 0
1"
#494
0"
#495
b1110111101011010 *
b1011100010 !
b1011100010 0
1"
#496
0"
#497
b1110111101011101 *
b1011100101 !
b1011100101 0
1"
#498
0"
#499
b1110111101100000 *
b1011101000 !
b1011101000 0
1"
#500
0"
#501
b1110111101100011 *
b1011101011 !
b1011101011 0
1"
#502
0"
#503
b1110111101100110 *
b1011101110 !
b1011101110 0
1"
#504
0"
#505
b1110111101101001 *
b1011110001 !
b1011110001 0
1"
#506
0"
#507
b1110111101101100 *
b1011110100 !
b1011110100 0
1"
#508
0"
#509
b1110111101101111 *
b1011110111 !
b1011110111 0
1"
#510
0"
#511
b1110111101110010 *
b1011111010 !
b1011111010 0
1"
#512
0"
#513
b1110111101110101 *
b1011111101 !
b1011111101 0
1"
#514
0"
#515
b1110111101111000 *
b1100000000 !
b1100000000 0
1"
#516
0"
#517
b1110111101111011 *
b1100000011 !
b1100000011 0
1"
#518
0"
#519
b1110111101111110 *
b1100000110 !
b1100000110 0
1"
#520
0"
#521
b1110111110000001 *
b1100001001 !
b1100001001 0
1"
#522
0"
#523
b1110111110000100 *
b1100001100 !
b1100001100 0
1"
#524
0"
#525
b1110111110000111 *
b1100001111 !
b1100001111 0
1"
#526
0"
#527
b1110111110001010 *
b1100010010 !
b1100010010 0
1"
#528
0"
#529
b1110111110001101 *
b1100010101 !
b1100010101 0
1"
#530
0"
#531
b1110111110010000 *
b1100011000 !
b1100011000 0
1"
#532
0"
#533
b1110111110010011 *
b1100011011 !
b1100011011 0
1"
#534
0"
#535
b1110111110010110 *
b1100011110 !
b1100011110 0
1"
#536
0"
#537
b1110111110011001 *
b1100100001 !
b1100100001 0
1"
#538
0"
#539
b1110111110011100 *
b1100100100 !
b1100100100 0
1"
#540
0"
#541
b1110111110011111 *
b1100100111 !
b1100100111 0
1"
#542
0"
#543
b1110111110100010 *
b1100101010 !
b1100101010 0
1"
#544
0"
#545
b1110111110100101 *
b1100101101 !
b1100101101 0
1"
#546
0"
#547
b1110111110101000 *
b1100110000 !
b1100110000 0
1"
#548
0"
#549
b1110111110101011 *
b1100110011 !
b1100110011 0
1"
#550
0"
#551
b1110111110101110 *
b1100110110 !
b1100110110 0
1"
#552
0"
#553
b1110111110110001 *
b1100111001 !
b1100111001 0
1"
#554
0"
#555
b1110111110110100 *
b1100111100 !
b1100111100 0
1"
#556
0"
#557
b1110111110110111 *
b1100111111 !
b1100111111 0
1"
#558
0"
#559
b1110111110111010 *
b1101000010 !
b1101000010 0
1"
#560
0"
#561
b1110111110111101 *
b1101000101 !
b1101000101 0
1"
#562
0"
#563
b1110111111000000 *
b1101001000 !
b1101001000 0
1"
#564
0"
#565
b1110111111000011 *
b1101001011 !
b1101001011 0
1"
#566
0"
#567
b1110111111000110 *
b1101001110 !
b1101001110 0
1"
#568
0"
#569
b1110111111001001 *
b1101010001 !
b1101010001 0
1"
#570
0"
#571
b1110111111001100 *
b1101010100 !
b1101010100 0
1"
#572
0"
#573
b1110111111001111 *
b1101010111 !
b1101010111 0
1"
#574
0"
#575
b1110111111010010 *
b1101011010 !
b1101011010 0
1"
#576
0"
#577
b1110111111010101 *
b1101011101 !
b1101011101 0
1"
#578
0"
#579
b1110111111011000 *
b1101100000 !
b1101100000 0
1"
#580
0"
#581
b1110111111011011 *
b1101100011 !
b1101100011 0
1"
#582
0"
#583
b1110111111011110 *
b1101100110 !
b1101100110 0
1"
#584
0"
#585
b1110111111100001 *
b1101101001 !
b1101101001 0
1"
#586
0"
#587
b1110111111100100 *
b1101101100 !
b1101101100 0
1"
#588
0"
#589
b1110111111100111 *
b1101101111 !
b1101101111 0
1"
#590
0"
#591
b1110111111101010 *
b1101110010 !
b1101110010 0
1"
#592
0"
#593
b1110111111101101 *
b1101110101 !
b1101110101 0
1"
#594
0"
#595
b1110111111110000 *
b1101111000 !
b1101111000 0
1"
#596
0"
#597
b1110111111110011 *
b1101111011 !
b1101111011 0
1"
#598
0"
#599
b1110111111110110 *
b1101111110 !
b1101111110 0
1"
#600
0"
#601
b1110111111111001 *
b1110000001 !
b1110000001 0
1"
#602
0"
#603
b1110111111111100 *
b1110000100 !
b1110000100 0
1"
#604
0"
#605
b1110111111111111 *
b1110000111 !
b1110000111 0
1"
#606
0"
#607
b1111000000000010 *
b1110001010 !
b1110001010 0
1"
#608
0"
#609
b1111000000000101 *
b1110001101 !
b1110001101 0
1"
#610
0"
#611
b1111000000001000 *
b1110010000 !
b1110010000 0
1"
#612
0"
#613
b1111000000001011 *
b1110010011 !
b1110010011 0
1"
#614
0"
#615
b1111000000001110 *
b1110010110 !
b1110010110 0
1"
#616
0"
#617
b1111000000010001 *
b1110011001 !
b1110011001 0
1"
#618
0"
#619
b1111000000010100 *
b1110011100 !
b1110011100 0
1"
#620
0"
#621
b1111000000010111 *
b1110011111 !
b1110011111 0
1"
#622
0"
#623
b1111000000011010 *
b1110100010 !
b1110100010 0
1"
#624
0"
#625
b1111000000011101 *
b1110100101 !
b1110100101 0
1"
#626
0"
#627
b1111000000100000 *
b1110101000 !
b1110101000 0
1"
#628
0"
#629
b1111000000100011 *
b1110101011 !
b1110101011 0
1"
#630
0"
#631
b1111000000100110 *
b1110101110 !
b1110101110 0
1"
#632
0"
#633
b1111000000101001 *
b1110110001 !
b1110110001 0
1"
#634
0"
#635
b1111000000101100 *
b1110110100 !
b1110110100 0
1"
#636
0"
#637
b1111000000101111 *
b1110110111 !
b1110110111 0
1"
#638
0"
#639
b1111000000110010 *
b1110111010 !
b1110111010 0
1"
#640
0"
#641
b1111000000110101 *
b1110111101 !
b1110111101 0
1"
#642
0"
#643
b1111000000111000 *
b1111000000 !
b1111000000 0
1"
#644
0"
#645
b1111000000111011 *
b1111000011 !
b1111000011 0
1"
#646
0"
#647
b1111000000111110 *
b1111000110 !
b1111000110 0
1"
#648
0"
#649
b1111000001000001 *
b1111001001 !
b1111001001 0
1"
#650
0"
#651
b1111000001000100 *
b1111001100 !
b1111001100 0
1"
#652
0"
#653
b1111000001000111 *
b1111001111 !
b1111001111 0
1"
#654
0"
#655
b1111000001001010 *
b1111010010 !
b1111010010 0
1"
#656
0"
#657
b1111000001001101 *
b1111010101 !
b1111010101 0
1"
#658
0"
#659
b1111000001010000 *
b1111011000 !
b1111011000 0
1"
#660
0"
#661
b1111000001010011 *
b1111011011 !
b1111011011 0
1"
#662
0"
#663
b1111000001010110 *
b1111011110 !
b1111011110 0
1"
#664
0"
#665
b1111000001011001 *
b1111100001 !
b1111100001 0
1"
#666
0"
#667
b1111000001011100 *
b1111100100 !
b1111100100 0
1"
#668
0"
#669
b1111000001011111 *
b1111100111 !
b1111100111 0
1"
#670
0"
#671
b1111000001100010 *
b1111101010 !
b1111101010 0
1"
#672
0"
#673
b1111000001100101 *
b1111101101 !
b1111101101 0
1"
#674
0"
#675
b1111000001101000 *
b1111110000 !
b1111110000 0
1"
#676
0"
#677
b1111000001101011 *
b1111110011 !
b1111110011 0
1"
#678
0"
#679
b1111000001101110 *
b1111110110 !
b1111110110 0
1"
#680
0"
#681
b1111000001110001 *
b1111111001 !
b1111111001 0
1"
#682
0"
#683
b1111000001110100 *
b1111111100 !
b1111111100 0
1"
#684
0"
#685
b1111000001110111 *
b1111111111 !
b1111111111 0
1"
#686
0"
#687
b1111000001111010 *
b10000000010 !
b10000000010 0
1"
#688
0"
#689
b1111000001111101 *
b10000000101 !
b10000000101 0
1"
#690
0"
#691
b1111000010000000 *
b10000001000 !
b10000001000 0
1"
#692
0"
#693
b1111000010000011 *
b10000001011 !
b10000001011 0
1"
#694
0"
#695
b1111000010000110 *
b10000001110 !
b10000001110 0
1"
#696
0"
